schemon_python_client/__init__.py
schemon_python_client/spark/__init__.py
schemon_python_client/spark/base/__init__.py
schemon_python_client/spark/base/base.py
schemon_python_client/spark/base/client.py
schemon_python_client/spark/base/credential_manager.py
schemon_python_client/spark/client/__init__.py
schemon_python_client/spark/client/databricks_client.py
schemon_python_client/spark/client/mssql_client.py
schemon_python_client/spark/client/s3_client.py
schemon_python_client/spark/credential_manager/__init__.py
schemon_python_client/spark/credential_manager/mssql_credential_manager.py
schemon_python_client/spark/credential_manager/mysql_credential_manager.py
schemon_python_client/spark/credential_manager/s3_credential_manager.py
schemon_python_client/spark/credential_manager/unity_catalog_credential_manager.py
schemon_python_client/spark/helper/__init__.py
schemon_python_client/spark/helper/common.py
schemon_python_client/spark/helper/custom_function.py
schemon_python_client/spark/helper/databricks.py
schemon_python_client/spark/helper/excel.py
schemon_python_client/spark/helper/file.py
schemon_python_client/spark/helper/fs.py
schemon_python_client/spark/helper/hive.py
schemon_python_client/spark/helper/mssql.py
schemon_python_client/spark/helper/pandas.py
schemon_python_client/spark/helper/stream.py
schemon_python_client/spark/helper/unity_catalog.py
schemon_python_client/spark/listener/__init__.py
schemon_python_client/spark/listener/streaming_trigger_listener.py
schemon_python_client/spark/reader/__init__.py
schemon_python_client/spark/reader/excel.py
schemon_python_client/spark/reader/flatfile.py
schemon_python_client-0.0.14.dist-info/LICENSE
schemon_python_client-0.0.14.dist-info/METADATA
schemon_python_client-0.0.14.dist-info/WHEEL
schemon_python_client-0.0.14.dist-info/top_level.txt
schemon_python_client-0.0.14.dist-info/RECORD
