Metadata-Version: 2.1
Name: schemon-python-client
Version: 0.0.14
Summary: UNKNOWN
Home-page: UNKNOWN
License: Apache License 2.0
Platform: UNKNOWN
Requires-Python: >=3.9
License-File: LICENSE
Requires-Dist: pyspark==3.5.0
Requires-Dist: cryptography==43.0.3
Requires-Dist: delta-spark==3.2.0
Requires-Dist: boto3==1.35.18
Requires-Dist: mysql-connector-python==9.1.0
Requires-Dist: schemon-python-logger
Requires-Dist: openpyxl==3.1.5
